index_of_refraction/__init__.py
index_of_refraction/data_io.py
index_of_refraction-1.0.dist-info/LICENSE
index_of_refraction-1.0.dist-info/METADATA
index_of_refraction-1.0.dist-info/WHEEL
index_of_refraction-1.0.dist-info/top_level.txt
index_of_refraction-1.0.dist-info/RECORD
